ev2gym/__init__.py
ev2gym/baselines/__init__.py
ev2gym/baselines/heuristics.py
ev2gym/baselines/gurobi_models/__init__.py
ev2gym/baselines/gurobi_models/profit_max.py
ev2gym/baselines/gurobi_models/tracking_error.py
ev2gym/baselines/gurobi_models/v2g_grid.py
ev2gym/baselines/mpc/V2GProfitMax.py
ev2gym/baselines/mpc/__init__.py
ev2gym/baselines/mpc/eMPC.py
ev2gym/baselines/mpc/eMPC_v2.py
ev2gym/baselines/mpc/mpc.py
ev2gym/baselines/mpc/ocmf_mpc.py
ev2gym/data/Netherlands_day-ahead-2015-2024.csv
ev2gym/data/__init__.py
ev2gym/data/development-in-power-dem.csv
ev2gym/data/distribution-of-arrival-weekend.csv
ev2gym/data/distribution-of-arrival.csv
ev2gym/data/distribution-of-charging.csv
ev2gym/data/distribution-of-connection-time.csv
ev2gym/data/distribution-of-energy-demand.csv
ev2gym/data/eda_day-ahead_prices.py
ev2gym/data/elaad_data_eda.py
ev2gym/data/ev_specs.json
ev2gym/data/ev_specs_ev_plus_phev.json
ev2gym/data/ev_specs_v2g_enabled2024.json
ev2gym/data/loads_eda.py
ev2gym/data/mean-demand-per-arrival.csv
ev2gym/data/mean-session-length-per.csv
ev2gym/data/pv_netherlands.csv
ev2gym/data/residential_loads.csv
ev2gym/data/time_of_connection_vs_hour.npy
ev2gym/data/network_data/__init__.py
ev2gym/example_config_files/PublicPST.yaml
ev2gym/example_config_files/V2GProfitMax.yaml
ev2gym/example_config_files/V2GProfitPlusLoads.yaml
ev2gym/example_config_files/V2Ggrid.yaml
ev2gym/example_config_files/__init__.py
ev2gym/example_config_files/charging_topology_10.json
ev2gym/models/__init__.py
ev2gym/models/data_augment.py
ev2gym/models/ev.py
ev2gym/models/ev2gym_env.py
ev2gym/models/ev_charger.py
ev2gym/models/grid.py
ev2gym/models/replay.py
ev2gym/models/transformer.py
ev2gym/models/grid_utility/__init__.py
ev2gym/models/grid_utility/grid_tensor.py
ev2gym/models/grid_utility/grid_utils.py
ev2gym/models/grid_utility/numbarize.py
ev2gym/rl_agent/__init__.py
ev2gym/rl_agent/action_wrappers.py
ev2gym/rl_agent/cost.py
ev2gym/rl_agent/noise_wrappers.py
ev2gym-2.0.0.dist-info/licenses/LICENSE
ev2gym-2.0.0.dist-info/METADATA
ev2gym-2.0.0.dist-info/WHEEL
ev2gym-2.0.0.dist-info/top_level.txt
ev2gym-2.0.0.dist-info/RECORD
