Metadata-Version: 2.4
Name: ev2gym
Version: 2.0.0
Summary: A realistic V2G simulator environment
Author: Stavros Orfanoudakis
Keywords: gym,Reinforcement Learning,V2X,V2G,G2V,EVs,ev2gym,Electric Vehicles,Electric Vehicle Simulator
Classifier: Programming Language :: Python :: 3
Classifier: License :: OSI Approved :: MIT License
Classifier: Operating System :: OS Independent
Requires-Python: >=3.6
License-File: LICENSE
Requires-Dist: gymnasium
Requires-Dist: pyyaml
Requires-Dist: matplotlib
Requires-Dist: pandas
Requires-Dist: networkx
Requires-Dist: gurobipy
Dynamic: author
Dynamic: classifier
Dynamic: description
Dynamic: description-content-type
Dynamic: keywords
Dynamic: license-file
Dynamic: requires-dist
Dynamic: requires-python
Dynamic: summary
